arprax_algorithms/__init__.py
arprax_algorithms/algorithms/__init__.py
arprax_algorithms/algorithms/sorting.py
arprax_algorithms/generators/__init__.py
arprax_algorithms/generators/core.py
arprax_algorithms/profiler/__init__.py
arprax_algorithms/profiler/profiler.py
arprax_algorithms/utils/__init__.py
arprax_algorithms-0.1.0.dist-info/METADATA
arprax_algorithms-0.1.0.dist-info/WHEEL
arprax_algorithms-0.1.0.dist-info/top_level.txt
arprax_algorithms-0.1.0.dist-info/RECORD
