Metadata-Version: 2.4
Name: arprax-algorithms
Version: 0.1.0
Summary: Industrial-Grade Algorithms by Arprax Lab
Author-email: Arprax Lab <lab@arprax.com>
Requires-Python: >=3.9
Provides-Extra: dev
Requires-Dist: build; extra == "dev"
Requires-Dist: twine; extra == "dev"
Requires-Dist: pytest; extra == "dev"
